anticheatservice/__init__.py
anticheatservice/tools.py
anticheatservice/utils.py
anticheatservice-0.0.13.dist-info/LICENSE
anticheatservice-0.0.13.dist-info/METADATA
anticheatservice-0.0.13.dist-info/WHEEL
anticheatservice-0.0.13.dist-info/top_level.txt
anticheatservice-0.0.13.dist-info/RECORD
